obrag/__init__.py
obrag/cli.py
obrag/config.py
obrag/indexing.py
obrag/logging.py
obrag/rag.py
obrag/utils.py
obrag-0.1.2.dist-info/licenses/LICENSE
obrag-0.1.2.dist-info/METADATA
obrag-0.1.2.dist-info/WHEEL
obrag-0.1.2.dist-info/entry_points.txt
obrag-0.1.2.dist-info/top_level.txt
obrag-0.1.2.dist-info/RECORD
